Metadata-Version: 1.0
Name: chinese-chess
Version: 0.0.2
Summary: This is my college project
Home-page: https://github.com
Author: Young_shool
Author-email: UNKNOWN
License: UNKNOWN
Platform: UNKNOWN
